{
  "main": {
    "id": "e3861dbf1ea3407e",
    "type": "split",
    "children": [
      {
        "id": "c0de77793e2ab59e",
        "type": "tabs",
        "children": [
          {
            "id": "7a27dde3cceff68c",
            "type": "leaf",
            "state": {
              "type": "markdown",
              "state": {
                "file": "tercer-parcial/retos-binary/04-two-sum.md",
                "mode": "source",
                "source": false
              }
            }
          }
        ]
      }
    ],
    "direction": "vertical"
  },
  "left": {
    "id": "4429d3843ba47817",
    "type": "split",
    "children": [
      {
        "id": "292f3453695e51d8",
        "type": "tabs",
        "children": [
          {
            "id": "20b9ffe455e8ba46",
            "type": "leaf",
            "state": {
              "type": "file-explorer",
              "state": {
                "sortOrder": "alphabetical"
              }
            }
          },
          {
            "id": "9ed7835f88463a99",
            "type": "leaf",
            "state": {
              "type": "search",
              "state": {
                "query": "",
                "matchingCase": false,
                "explainSearch": false,
                "collapseAll": false,
                "extraContext": false,
                "sortOrder": "alphabetical"
              }
            }
          },
          {
            "id": "3eb1f7302110e9f2",
            "type": "leaf",
            "state": {
              "type": "starred",
              "state": {}
            }
          },
          {
            "id": "556bc77c82bd3d3f",
            "type": "leaf",
            "state": {
              "type": "bookmarks",
              "state": {}
            }
          }
        ]
      }
    ],
    "direction": "horizontal",
    "width": 276.5
  },
  "right": {
    "id": "7eee77f474dbc0e5",
    "type": "split",
    "children": [
      {
        "id": "4082258e9e80b41e",
        "type": "tabs",
        "children": [
          {
            "id": "22c3de9ca11d18fc",
            "type": "leaf",
            "state": {
              "type": "backlink",
              "state": {
                "file": "tercer-parcial/retos-binary/04-two-sum.md",
                "collapseAll": false,
                "extraContext": false,
                "sortOrder": "alphabetical",
                "showSearch": false,
                "searchQuery": "",
                "backlinkCollapsed": false,
                "unlinkedCollapsed": true
              }
            }
          },
          {
            "id": "99de7e6cd7b5746c",
            "type": "leaf",
            "state": {
              "type": "outgoing-link",
              "state": {
                "file": "tercer-parcial/retos-binary/04-two-sum.md",
                "linksCollapsed": false,
                "unlinkedCollapsed": true
              }
            }
          },
          {
            "id": "6926f7afc49c361c",
            "type": "leaf",
            "state": {
              "type": "tag",
              "state": {
                "sortOrder": "frequency",
                "useHierarchy": true
              }
            }
          },
          {
            "id": "194c8dc7a13728aa",
            "type": "leaf",
            "state": {
              "type": "outline",
              "state": {
                "file": "tercer-parcial/retos-binary/04-two-sum.md"
              }
            }
          }
        ]
      }
    ],
    "direction": "horizontal",
    "width": 300,
    "collapsed": true
  },
  "left-ribbon": {
    "hiddenItems": {
      "switcher:Open quick switcher": false,
      "graph:Open graph view": false,
      "canvas:Create new canvas": false,
      "daily-notes:Open today's daily note": false,
      "templates:Insert template": false,
      "command-palette:Open command palette": false
    }
  },
  "active": "7a27dde3cceff68c",
  "lastOpenFiles": [
    "tercer-parcial/retos-binary/03-clutter-overflow.md",
    "tercer-parcial/retos-binary/04-two-sum.md",
    "tercer-parcial/Plantilla.md",
    "tercer-parcial/retos-binary/02-Local Target.md",
    "retos-Binary-Exploitation/03-Buffer Overflow 1.md",
    "tercer-parcial/retos-binary/01-Picker IV.md",
    "tercer-parcial/retos-reversing/07-GDB baby step 2.md",
    "tercer-parcial/retos-reversing/06-GDB baby step 1.md",
    "tercer-parcial/retos-reversing/05-Bit-O-Asm-4.md",
    "tercer-parcial/retos-reversing/04-Bit-O-Asm-3.md",
    "tercer-parcial/retos-reversing/03-Bit-O-Asm-2.md",
    "tercer-parcial/retos-reversing/01-ASCII FTW.md",
    "tercer-parcial/retos-reversing/02-Bit-O-Asm-1.md",
    "tercer-parcial/retos-crypto/05-SRA.md",
    "tercer-parcial/retos-crypto/04-Vigenere.md",
    "tercer-parcial/retos-crypto/03-transposition-trial.md",
    "tercer-parcial/retos-crypto/02-Mr-Wolrdwide.md",
    "tercer-parcial/retos-crypto/01-Flags.md",
    "retos-Binary-Exploitation/05-Stonks.md",
    "tercer-parcial/retos-binary",
    "tercer-parcial/retos-reversing",
    "tercer-parcial/retos-crypto",
    "tercer-parcial",
    "retos-Binary-Exploitation/04-flag leak.md",
    "retos-Binary-Exploitation/Plantilla.md",
    "retos-Binary-Exploitation/02-Buffer Overflow 0.md",
    "retos-Binary-Exploitation/01-basic-file-exploit.md",
    "retos-Binary-Exploitation",
    "retos-RE/11-Safe opener 2.md",
    "retos-RE/10-reverse_cipher.md",
    "retos-RE/Plantilla 1.md",
    "retos-RE",
    "retos-Crypto",
    "segundo-parcial/retos-forensic",
    "segundo-parcial/retos-web",
    "segundo-parcial",
    "Pasted image 20230322120823.png",
    "Pasted image 20230322120811.png",
    "Pasted image 20230313183507.png"
  ]
}